{
    "Data Source": "raw:com.google.calories.expended:running.tracker.gps.map:",
    "Data Points": [
        {"fitValue":[{"value":{"fpVal":158.60000610351562}}],"originDataSourceId":"","endTimeNanos":1704755949787000000,"dataTypeName":"com.google.calories.expended","startTimeNanos":1704755281590000000,"modifiedTimeMillis":1720635573499,"rawTimestampNanos":0},
        {"fitValue":[{"value":{"fpVal":158.10000610351562}}],"originDataSourceId":"","endTimeNanos":1704840865534000000,"dataTypeName":"com.google.calories.expended","startTimeNanos":1704840202927000000,"modifiedTimeMillis":1720635573499,"rawTimestampNanos":0},
        {"fitValue":[{"value":{"fpVal":141.1999969482422}}],"originDataSourceId":"","endTimeNanos":1704939286952000000,"dataTypeName":"com.google.calories.expended","startTimeNanos":1704938725810000000,"modifiedTimeMillis":1720635573499,"rawTimestampNanos":0},
        {"fitValue":[{"value":{"fpVal":151.5}}],"originDataSourceId":"","endTimeNanos":1705012746408000000,"dataTypeName":"com.google.calories.expended","startTimeNanos":1705012129713000000,"modifiedTimeMillis":1720635573499,"rawTimestampNanos":0},
        {"fitValue":[{"value":{"fpVal":235.10000610351562}}],"originDataSourceId":"","endTimeNanos":1705273892543000000,"dataTypeName":"com.google.calories.expended","startTimeNanos":1705272854977000000,"modifiedTimeMillis":1720635573499,"rawTimestampNanos":0},
        {"fitValue":[{"value":{"fpVal":142.39999389648438}}],"originDataSourceId":"","endTimeNanos":1705358871294000000,"dataTypeName":"com.google.calories.expended","startTimeNanos":1705358287504000000,"modifiedTimeMillis":1720635573499,"rawTimestampNanos":0},
        {"fitValue":[{"value":{"fpVal":73.80000305175781}}],"originDataSourceId":"","endTimeNanos":1705446426286000000,"dataTypeName":"com.google.calories.expended","startTimeNanos":1705445796023000000,"modifiedTimeMillis":1720635573499,"rawTimestampNanos":0},
        {"fitValue":[{"value":{"fpVal":236.10000610351562}}],"originDataSourceId":"","endTimeNanos":1705860082408000000,"dataTypeName":"com.google.calories.expended","startTimeNanos":1705859024258000000,"modifiedTimeMillis":1720635573499,"rawTimestampNanos":0},
        {"fitValue":[{"value":{"fpVal":153.89999389648438}}],"originDataSourceId":"","endTimeNanos":1705947583085000000,"dataTypeName":"com.google.calories.expended","startTimeNanos":1705946899101000000,"modifiedTimeMillis":1720635573499,"rawTimestampNanos":0},
        {"fitValue":[{"value":{"fpVal":153.1999969482422}}],"originDataSourceId":"","endTimeNanos":1706050834886000000,"dataTypeName":"com.google.calories.expended","startTimeNanos":1706050156362000000,"modifiedTimeMillis":1720635573499,"rawTimestampNanos":0},
        {"fitValue":[{"value":{"fpVal":157.5}}],"originDataSourceId":"","endTimeNanos":1706553237911000000,"dataTypeName":"com.google.calories.expended","startTimeNanos":1706552583884000000,"modifiedTimeMillis":1720635573499,"rawTimestampNanos":0},
        {"fitValue":[{"value":{"fpVal":144.6999969482422}}],"originDataSourceId":"","endTimeNanos":1707103177572000000,"dataTypeName":"com.google.calories.expended","startTimeNanos":1707102590994000000,"modifiedTimeMillis":1720635573499,"rawTimestampNanos":0},
        {"fitValue":[{"value":{"fpVal":31.5}}],"originDataSourceId":"","endTimeNanos":1708732007822000000,"dataTypeName":"com.google.calories.expended","startTimeNanos":1708730961233000000,"modifiedTimeMillis":1720635573499,"rawTimestampNanos":0},
        {"fitValue":[{"value":{"fpVal":236.89999389648438}}],"originDataSourceId":"","endTimeNanos":1709334230852000000,"dataTypeName":"com.google.calories.expended","startTimeNanos":1709333183981000000,"modifiedTimeMillis":1720635573499,"rawTimestampNanos":0},
        {"fitValue":[{"value":{"fpVal":180.10000610351562}}],"originDataSourceId":"","endTimeNanos":1709698994445000000,"dataTypeName":"com.google.calories.expended","startTimeNanos":1709698219946000000,"modifiedTimeMillis":1720635573499,"rawTimestampNanos":0},
        {"fitValue":[{"value":{"fpVal":146.1999969482422}}],"originDataSourceId":"","endTimeNanos":1710133755573000000,"dataTypeName":"com.google.calories.expended","startTimeNanos":1710133151238000000,"modifiedTimeMillis":1720635573499,"rawTimestampNanos":0},
        {"fitValue":[{"value":{"fpVal":157.60000610351562}}],"originDataSourceId":"","endTimeNanos":1712034941876000000,"dataTypeName":"com.google.calories.expended","startTimeNanos":1712034274088000000,"modifiedTimeMillis":1720635573499,"rawTimestampNanos":0},
        {"fitValue":[{"value":{"fpVal":235}}],"originDataSourceId":"","endTimeNanos":1712902667868000000,"dataTypeName":"com.google.calories.expended","startTimeNanos":1712901571151000000,"modifiedTimeMillis":1720635573499,"rawTimestampNanos":0},
        {"fitValue":[{"value":{"fpVal":161.8000030517578}}],"originDataSourceId":"","endTimeNanos":1713250644784000000,"dataTypeName":"com.google.calories.expended","startTimeNanos":1713249945555000000,"modifiedTimeMillis":1720635573499,"rawTimestampNanos":0},
        {"fitValue":[{"value":{"fpVal":25.600000381469727}}],"originDataSourceId":"","endTimeNanos":1713745829743000000,"dataTypeName":"com.google.calories.expended","startTimeNanos":1713744936649000000,"modifiedTimeMillis":1720635573499,"rawTimestampNanos":0},
        {"fitValue":[{"value":{"fpVal":179.10000610351562}}],"originDataSourceId":"","endTimeNanos":1713830203834000000,"dataTypeName":"com.google.calories.expended","startTimeNanos":1713829201860000000,"modifiedTimeMillis":1720635573499,"rawTimestampNanos":0},
        {"fitValue":[{"value":{"fpVal":144.5}}],"originDataSourceId":"","endTimeNanos":1714094532411000000,"dataTypeName":"com.google.calories.expended","startTimeNanos":1714093924623000000,"modifiedTimeMillis":1720635573499,"rawTimestampNanos":0},
        {"fitValue":[{"value":{"fpVal":116.9000015258789}}],"originDataSourceId":"","endTimeNanos":1714180059534000000,"dataTypeName":"com.google.calories.expended","startTimeNanos":1714178997568000000,"modifiedTimeMillis":1720635573499,"rawTimestampNanos":0},
        {"fitValue":[{"value":{"fpVal":165.6999969482422}}],"originDataSourceId":"","endTimeNanos":1714348815320000000,"dataTypeName":"com.google.calories.expended","startTimeNanos":1714348103656000000,"modifiedTimeMillis":1720635573499,"rawTimestampNanos":0},
        {"fitValue":[{"value":{"fpVal":41.79999923706055}}],"originDataSourceId":"","endTimeNanos":1714436994358000000,"dataTypeName":"com.google.calories.expended","startTimeNanos":1714436393558000000,"modifiedTimeMillis":1720635573499,"rawTimestampNanos":0},
        {"fitValue":[{"value":{"fpVal":154.3000030517578}}],"originDataSourceId":"","endTimeNanos":1714523273242000000,"dataTypeName":"com.google.calories.expended","startTimeNanos":1714522638408000000,"modifiedTimeMillis":1720635573499,"rawTimestampNanos":0},
        {"fitValue":[{"value":{"fpVal":160.3000030517578}}],"originDataSourceId":"","endTimeNanos":1714972044102000000,"dataTypeName":"com.google.calories.expended","startTimeNanos":1714971336577000000,"modifiedTimeMillis":1720635573499,"rawTimestampNanos":0},
        {"fitValue":[{"value":{"fpVal":242.89999389648438}}],"originDataSourceId":"","endTimeNanos":1715041049544000000,"dataTypeName":"com.google.calories.expended","startTimeNanos":1715040007040000000,"modifiedTimeMillis":1720635573499,"rawTimestampNanos":0},
        {"fitValue":[{"value":{"fpVal":141.60000610351562}}],"originDataSourceId":"","endTimeNanos":1715129045096000000,"dataTypeName":"com.google.calories.expended","startTimeNanos":1715128477112000000,"modifiedTimeMillis":1720635573499,"rawTimestampNanos":0},
        {"fitValue":[{"value":{"fpVal":236}}],"originDataSourceId":"","endTimeNanos":1715214983880000000,"dataTypeName":"com.google.calories.expended","startTimeNanos":1715213948139000000,"modifiedTimeMillis":1720635573499,"rawTimestampNanos":0},
        {"fitValue":[{"value":{"fpVal":138.60000610351562}}],"originDataSourceId":"","endTimeNanos":1716337593819000000,"dataTypeName":"com.google.calories.expended","startTimeNanos":1716337038412000000,"modifiedTimeMillis":1720635573499,"rawTimestampNanos":0},
        {"fitValue":[{"value":{"fpVal":13.5}}],"originDataSourceId":"","endTimeNanos":1716769063997000000,"dataTypeName":"com.google.calories.expended","startTimeNanos":1716768894301000000,"modifiedTimeMillis":1720635573499,"rawTimestampNanos":0},
        {"fitValue":[{"value":{"fpVal":1.7999999523162842}}],"originDataSourceId":"","endTimeNanos":1716925573262000000,"dataTypeName":"com.google.calories.expended","startTimeNanos":1716925550496000000,"modifiedTimeMillis":1720635573499,"rawTimestampNanos":0},
        {"fitValue":[{"value":{"fpVal":1274.199951171875}}],"originDataSourceId":"","endTimeNanos":1717460384849000000,"dataTypeName":"com.google.calories.expended","startTimeNanos":1717443727311000000,"modifiedTimeMillis":1720635573499,"rawTimestampNanos":0}
    ]
}